phase-0.3.0.data/purelib/phase/Band.dll
phase-0.3.0.data/purelib/phase/Basler.Pylon.dll
phase-0.3.0.data/purelib/phase/DibGiomUtilities.dll
phase-0.3.0.data/purelib/phase/DigTKCameraCalib.dll
phase-0.3.0.data/purelib/phase/DigTKIO.dll
phase-0.3.0.data/purelib/phase/DigTKMatch.dll
phase-0.3.0.data/purelib/phase/DigTKMultiGPUMatcherIntegration.dll
phase-0.3.0.data/purelib/phase/DigTKUtilities.dll
phase-0.3.0.data/purelib/phase/FilterBase.dll
phase-0.3.0.data/purelib/phase/FirmwareUpdate_MD_VC141_v3_1_Basler_pylon.dll
phase-0.3.0.data/purelib/phase/GCBase_MD_VC141_v3_1_Basler_pylon.dll
phase-0.3.0.data/purelib/phase/GenApi_MD_VC141_v3_1_Basler_pylon.dll
phase-0.3.0.data/purelib/phase/Geometry.dll
phase-0.3.0.data/purelib/phase/GraphObject2d.dll
phase-0.3.0.data/purelib/phase/GraphObject3d.dll
phase-0.3.0.data/purelib/phase/InternationalisationRegistry.dll
phase-0.3.0.data/purelib/phase/KernelFilterBase.dll
phase-0.3.0.data/purelib/phase/Log_MD_VC141_v3_1_Basler_pylon.dll
phase-0.3.0.data/purelib/phase/MathParser_MD_VC141_v3_1_Basler_pylon.dll
phase-0.3.0.data/purelib/phase/NodeMapData_MD_VC141_v3_1_Basler_pylon.dll
phase-0.3.0.data/purelib/phase/ParameterPool.dll
phase-0.3.0.data/purelib/phase/PhobosIntegration.dll
phase-0.3.0.data/purelib/phase/PhobosIntegrationEnglish.trl
phase-0.3.0.data/purelib/phase/ProgramOptions.dll
phase-0.3.0.data/purelib/phase/Progress.dll
phase-0.3.0.data/purelib/phase/PylonBase_v6_3.dll
phase-0.3.0.data/purelib/phase/PylonC_v6_3.dll
phase-0.3.0.data/purelib/phase/PylonCamEmu_v6_3_TL.dll
phase-0.3.0.data/purelib/phase/PylonGUI_v6_3.dll
phase-0.3.0.data/purelib/phase/PylonGigE_v6_3_TL.dll
phase-0.3.0.data/purelib/phase/PylonGtc_v6_3_TL.dll
phase-0.3.0.data/purelib/phase/PylonUsb_v6_3_TL.dll
phase-0.3.0.data/purelib/phase/PylonUtility_v6_3.dll
phase-0.3.0.data/purelib/phase/Qt5Core.dll
phase-0.3.0.data/purelib/phase/Qt5Gui.dll
phase-0.3.0.data/purelib/phase/Qt5PrintSupport.dll
phase-0.3.0.data/purelib/phase/Qt5Svg.dll
phase-0.3.0.dist-info/LICENSE
phase-0.3.0.dist-info/METADATA
phase-0.3.0.dist-info/WHEEL
phase-0.3.0.dist-info/top_level.txt
phase-0.3.0.dist-info/RECORD
